{"ai_questions": [ "Self-driving cars" , "Robot caregivers" , "Hiring employees" , "Diagnosising disease" , "Setting bail" , "Prescribing medication" , "Faking news" , "Automating jobs"  ] , "test_questions": [{"model_id": "tree_383", "possible_answers": ["Income <= 50K", "Income > 50K"], "feature_names": ["Age", "Education_Num", "Capital Gain", "Martial Status"], "question_id": "1124", "feature_values": ["50", "9", "0", "Married civ spouse"], "correct_answer": "Income > 50K", "question_number": "0"}, {"model_id": "tree_383", "possible_answers": ["Income <= 50K", "Income > 50K"], "feature_names": ["Age", "Education_Num", "Capital Gain", "Martial Status"], "question_id": "3399", "feature_values": ["20", "10", "0", "Never married"], "correct_answer": "Income <= 50K", "question_number": "1"}, {"model_id": "tree_383", "possible_answers": ["Income <= 50K", "Income > 50K"], "feature_names": ["Age", "Education_Num", "Capital Gain", "Martial Status"], "question_id": "2133", "feature_values": ["37", "13", "0", "Married civ spouse"], "correct_answer": "Income > 50K", "question_number": "2"}, {"model_id": "tree_383", "possible_answers": ["Income <= 50K", "Income > 50K"], "feature_names": ["Age", "Education_Num", "Capital Gain", "Martial Status"], "question_id": "5937", "feature_values": ["37", "14", "4787", "Divorced"], "correct_answer": "Income > 50K", "question_number": "3"}, {"model_id": "tree_383", "possible_answers": ["Income <= 50K", "Income > 50K"], "feature_names": ["Age", "Education_Num", "Capital Gain", "Martial Status"], "question_id": "4353", "feature_values": ["29", "9", "0", "Separated"], "correct_answer": "Income <= 50K", "question_number": "4"}, {"model_id": "tree_383", "possible_answers": ["Income <= 50K", "Income > 50K"], "feature_names": ["Age", "Education_Num", "Capital Gain", "Martial Status"], "question_id": "120", "feature_values": ["46", "14", "0", "Married civ spouse"], "correct_answer": "Income > 50K", "question_number": "5"}, {"model_id": "tree_383", "possible_answers": ["Income <= 50K", "Income > 50K"], "feature_names": ["Age", "Education_Num", "Capital Gain", "Martial Status"], "question_id": "5083", "feature_values": ["42", "13", "99999", "Married civ spouse"], "correct_answer": "Income > 50K", "question_number": "6"}, {"model_id": "tree_383", "possible_answers": ["Income <= 50K", "Income > 50K"], "feature_names": ["Age", "Education_Num", "Capital Gain", "Martial Status"], "question_id": "2761", "feature_values": ["46", "9", "0", "Married civ spouse"], "correct_answer": "Income > 50K", "question_number": "7"}], "practice_questions": [{"model_id": "tree_139", "question_id": "1124", "feature_names": ["Education_Num", "Capital Gain", "Hours per week", "Martial Status", "Occupation"], "possible_answers": ["Income <= 50K", "Income > 50K"], "feature_values": ["9", "0", "55", "Married civ spouse", "Sales"], "correct_answer": "Income > 50K", "question_number": "0"}, {"model_id": "tree_139", "question_id": "3399", "feature_names": ["Education_Num", "Capital Gain", "Hours per week", "Martial Status", "Occupation"], "possible_answers": ["Income <= 50K", "Income > 50K"], "feature_values": ["10", "0", "40", "Never married", "Transport moving"], "correct_answer": "Income <= 50K", "question_number": "1"}, {"model_id": "tree_139", "question_id": "2133", "feature_names": ["Education_Num", "Capital Gain", "Hours per week", "Martial Status", "Occupation"], "possible_answers": ["Income <= 50K", "Income > 50K"], "feature_values": ["13", "0", "40", "Married civ spouse", "Prof specialty"], "correct_answer": "Income > 50K", "question_number": "2"}, {"model_id": "tree_139", "question_id": "5937", "feature_names": ["Education_Num", "Capital Gain", "Hours per week", "Martial Status", "Occupation"], "possible_answers": ["Income <= 50K", "Income > 50K"], "feature_values": ["14", "4787", "40", "Divorced", "Prof specialty"], "correct_answer": "Income <= 50K", "question_number": "3"}, {"model_id": "tree_139", "question_id": "4353", "feature_names": ["Education_Num", "Capital Gain", "Hours per week", "Martial Status", "Occupation"], "possible_answers": ["Income <= 50K", "Income > 50K"], "feature_values": ["9", "0", "30", "Separated", "Transport moving"], "correct_answer": "Income <= 50K", "question_number": "4"}, {"model_id": "tree_139", "question_id": "120", "feature_names": ["Education_Num", "Capital Gain", "Hours per week", "Martial Status", "Occupation"], "possible_answers": ["Income <= 50K", "Income > 50K"], "feature_values": ["14", "0", "20", "Married civ spouse", "Adm clerical"], "correct_answer": "Income > 50K", "question_number": "5"}], "model_id": "tree_383", "practice_model_id": "tree_139"}